nordypy/__init__.py
nordypy/_athena.py
nordypy/_command_generation.py
nordypy/_datasource.py
nordypy/_init_methods.py
nordypy/_knowledge_repo_utils.py
nordypy/_nordstrom_rock_it.py
nordypy/_redshift_utils.py
nordypy/_s3.py
nordypy/_secret.py
nordypy/make_one_pager.py
nordypy/package_resources/assets/default/.gitignore
nordypy/package_resources/assets/default/README.md
nordypy/package_resources/assets/default/config.yaml
nordypy/package_resources/assets/default/folder_structure.yaml
nordypy/package_resources/assets/default/therock.txt
nordypy/package_resources/assets/default/therock25.txt
nordypy/package_resources/document_templates/default/one_page.md
nordypy-2.1.3.dist-info/LICENSE
nordypy-2.1.3.dist-info/WHEEL
nordypy-2.1.3.dist-info/METADATA
nordypy-2.1.3.dist-info/RECORD
